tspnoq.py
tspnoq-0.0.6.dist-info/METADATA
tspnoq-0.0.6.dist-info/RECORD
tspnoq-0.0.6.dist-info/WHEEL
tspnoq-0.0.6.dist-info/top_level.txt
